LICENSE
MANIFEST.in
README.rst
setup.py
django_wymeditor.egg-info/PKG-INFO
django_wymeditor.egg-info/SOURCES.txt
django_wymeditor.egg-info/dependency_links.txt
django_wymeditor.egg-info/not-zip-safe
django_wymeditor.egg-info/top_level.txt
wymeditor/__init__.py
wymeditor/admin.py
wymeditor/models.py
wymeditor/widgets.py
wymeditor/static/js/load_wymeditor.js
wymeditor/static/wymeditor/jquery.wymeditor.js
wymeditor/static/wymeditor/jquery.wymeditor.min.js
wymeditor/static/wymeditor/jquery.wymeditor.pack.js
wymeditor/static/wymeditor/iframe/default/lbl-blockquote.png
wymeditor/static/wymeditor/iframe/default/lbl-h1.png
wymeditor/static/wymeditor/iframe/default/lbl-h2.png
wymeditor/static/wymeditor/iframe/default/lbl-h3.png
wymeditor/static/wymeditor/iframe/default/lbl-h4.png
wymeditor/static/wymeditor/iframe/default/lbl-h5.png
wymeditor/static/wymeditor/iframe/default/lbl-h6.png
wymeditor/static/wymeditor/iframe/default/lbl-p.png
wymeditor/static/wymeditor/iframe/default/lbl-pre.png
wymeditor/static/wymeditor/iframe/default/wymiframe.css
wymeditor/static/wymeditor/iframe/default/wymiframe.html
wymeditor/static/wymeditor/lang/bg.js
wymeditor/static/wymeditor/lang/ca.js
wymeditor/static/wymeditor/lang/cs.js
wymeditor/static/wymeditor/lang/cy.js
wymeditor/static/wymeditor/lang/de.js
wymeditor/static/wymeditor/lang/en.js
wymeditor/static/wymeditor/lang/es.js
wymeditor/static/wymeditor/lang/fa.js
wymeditor/static/wymeditor/lang/fi.js
wymeditor/static/wymeditor/lang/fr.js
wymeditor/static/wymeditor/lang/gl.js
wymeditor/static/wymeditor/lang/he.js
wymeditor/static/wymeditor/lang/hr.js
wymeditor/static/wymeditor/lang/hu.js
wymeditor/static/wymeditor/lang/it.js
wymeditor/static/wymeditor/lang/nb.js
wymeditor/static/wymeditor/lang/nl.js
wymeditor/static/wymeditor/lang/nn.js
wymeditor/static/wymeditor/lang/pl.js
wymeditor/static/wymeditor/lang/pt-br.js
wymeditor/static/wymeditor/lang/pt.js
wymeditor/static/wymeditor/lang/ru.js
wymeditor/static/wymeditor/lang/sv.js
wymeditor/static/wymeditor/lang/tr.js
wymeditor/static/wymeditor/lang/zh_cn.js
wymeditor/static/wymeditor/plugins/embed/jquery.wymeditor.embed.js
wymeditor/static/wymeditor/plugins/fullscreen/icon_fullscreen.gif
