Metadata-Version: 1.1
Name: django-wymeditor
Version: 1.0
Summary: A Django application that contains a widget to render a form field with a WYMEditor interface.
Home-page: https://github.com/gabrielhurley/django-wymeditor
Author: Gabriel Hurley
Author-email: gabriel@strikeawe.com
License: BSD
Download-URL: git://github.com/gabrielhurley/django-wymeditor.git
Platform: UNKNOWN
Classifier: Development Status :: 4 - Beta
Classifier: Environment :: Web Environment
Classifier: Framework :: Django
Classifier: Intended Audience :: Developers
Classifier: License :: OSI Approved :: BSD License
Classifier: Operating System :: OS Independent
Classifier: Programming Language :: Python
Classifier: Topic :: Software Development :: Libraries :: Python Modules
Classifier: Topic :: Utilities
